{"namedChunkGroups":{"polyfill":{"name":"polyfill","assets":[{"name":"webpack-runtime-0df09463927bf8cab439.js","size":4188},{"name":"polyfill-459c1a21a013462a8859.js","size":82578}],"filteredAssets":0,"assetsSize":86766,"filteredAuxiliaryAssets":2,"auxiliaryAssetsSize":218977},"app":{"name":"app","assets":[{"name":"webpack-runtime-0df09463927bf8cab439.js","size":4188},{"name":"framework-69f634ee018b8a08c1b0.js","size":128870},{"name":"app-08397d26174811c396ad.js","size":49294}],"filteredAssets":0,"assetsSize":182352,"filteredAuxiliaryAssets":3,"auxiliaryAssetsSize":542541},"component---src-pages-404-js":{"name":"component---src-pages-404-js","assets":[{"name":"component---src-pages-404-js-72b0c4cc06be11974d1d.js","size":800}],"filteredAssets":0,"assetsSize":800,"filteredAuxiliaryAssets":1,"auxiliaryAssetsSize":1881},"component---src-pages-index-js":{"name":"component---src-pages-index-js","assets":[{"name":"styles.5f51c7f60067ba8460d3.css","size":10871},{"name":"component---src-pages-index-js-c1f9c8e48bc9a80969a6.js","size":38025}],"filteredAssets":0,"assetsSize":48896,"filteredAuxiliaryAssets":1,"auxiliaryAssetsSize":115809}},"assetsByChunkName":{"polyfill":["webpack-runtime-0df09463927bf8cab439.js","polyfill-459c1a21a013462a8859.js"],"app":["webpack-runtime-0df09463927bf8cab439.js","framework-69f634ee018b8a08c1b0.js","app-08397d26174811c396ad.js"],"component---src-pages-404-js":["component---src-pages-404-js-72b0c4cc06be11974d1d.js"],"component---src-pages-index-js":["styles.5f51c7f60067ba8460d3.css","component---src-pages-index-js-c1f9c8e48bc9a80969a6.js"]},"childAssetsByChunkName":{}}